cli/__init__.py
cli/main.py
config/__init__.py
config/config.py
log/LOG.py
log/__init__.py
report/__init__.py
deploy_cmd_viton-1.0.1.dist-info/METADATA
deploy_cmd_viton-1.0.1.dist-info/WHEEL
deploy_cmd_viton-1.0.1.dist-info/entry_points.txt
deploy_cmd_viton-1.0.1.dist-info/top_level.txt
deploy_cmd_viton-1.0.1.dist-info/RECORD
