Metadata-Version: 2.1
Name: deploy-cmd-viton
Version: 1.0.1
Summary: A small deploy_cmd_viton package
Author-email: viton <viton@gmail.com>
Classifier: Programming Language :: Python :: 3
Classifier: License :: OSI Approved :: MIT License
Classifier: Operating System :: OS Independent
Requires-Python: >=3.8
Requires-Dist: setuptools
Requires-Dist: requests
